openai_sdk_helpers/__init__.py
openai_sdk_helpers/cli.py
openai_sdk_helpers/environment.py
openai_sdk_helpers/errors.py
openai_sdk_helpers/files_api.py
openai_sdk_helpers/logging.py
openai_sdk_helpers/py.typed
openai_sdk_helpers/settings.py
openai_sdk_helpers/tools.py
openai_sdk_helpers/types.py
openai_sdk_helpers/agent/__init__.py
openai_sdk_helpers/agent/base.py
openai_sdk_helpers/agent/classifier.py
openai_sdk_helpers/agent/configuration.py
openai_sdk_helpers/agent/coordinator.py
openai_sdk_helpers/agent/files.py
openai_sdk_helpers/agent/runner.py
openai_sdk_helpers/agent/summarizer.py
openai_sdk_helpers/agent/translator.py
openai_sdk_helpers/agent/utils.py
openai_sdk_helpers/agent/validator.py
openai_sdk_helpers/agent/search/__init__.py
openai_sdk_helpers/agent/search/base.py
openai_sdk_helpers/agent/search/vector.py
openai_sdk_helpers/agent/search/web.py
openai_sdk_helpers/enums/__init__.py
openai_sdk_helpers/enums/base.py
openai_sdk_helpers/extract/__init__.py
openai_sdk_helpers/extract/extractor.py
openai_sdk_helpers/extract/generator.py
openai_sdk_helpers/prompt/__init__.py
openai_sdk_helpers/prompt/base.py
openai_sdk_helpers/prompt/classifier.jinja
openai_sdk_helpers/prompt/extractor_config_agent_instructions.jinja
openai_sdk_helpers/prompt/extractor_config_generator.jinja
openai_sdk_helpers/prompt/extractor_config_generator_instructions.jinja
openai_sdk_helpers/prompt/extractor_prompt_optimizer_agent_instructions.jinja
openai_sdk_helpers/prompt/extractor_prompt_optimizer_request.jinja
openai_sdk_helpers/prompt/summarizer.jinja
openai_sdk_helpers/prompt/translator.jinja
openai_sdk_helpers/prompt/validator.jinja
openai_sdk_helpers/prompt/vector_planner.jinja
openai_sdk_helpers/prompt/vector_search.jinja
openai_sdk_helpers/prompt/vector_writer.jinja
openai_sdk_helpers/response/__init__.py
openai_sdk_helpers/response/base.py
openai_sdk_helpers/response/configuration.py
openai_sdk_helpers/response/files.py
openai_sdk_helpers/response/messages.py
openai_sdk_helpers-0.6.2.dist-info/METADATA
openai_sdk_helpers-0.6.2.dist-info/WHEEL
openai_sdk_helpers-0.6.2.dist-info/entry_points.txt
openai_sdk_helpers-0.6.2.dist-info/licenses/LICENSE
openai_sdk_helpers-0.6.2.dist-info/RECORD
