Metadata-Version: 2.4
Name: openai-sdk-helpers
Version: 0.6.2
Summary: Composable helpers for OpenAI SDK agents, prompts, and storage
Author: openai-sdk-helpers maintainers
License: MIT
License-File: LICENSE
Classifier: Development Status :: 4 - Beta
Classifier: Intended Audience :: Developers
Classifier: License :: OSI Approved :: MIT License
Classifier: Programming Language :: Python :: 3
Classifier: Programming Language :: Python :: 3.10
Classifier: Programming Language :: Python :: 3.11
Classifier: Programming Language :: Python :: 3.12
Classifier: Programming Language :: Python :: 3.13
Classifier: Topic :: Software Development :: Libraries :: Python Modules
Classifier: Typing :: Typed
Requires-Python: >=3.10
Requires-Dist: jinja2
Requires-Dist: langextract
Requires-Dist: openai-agents<1.0.0,>=0.6.4
Requires-Dist: openai<3.0.0,>=2.14.0
Requires-Dist: pydantic<3,>=2.7
Requires-Dist: python-dotenv
Requires-Dist: streamlit
Requires-Dist: typing-extensions<5,>=4.15.0
Provides-Extra: dev
Requires-Dist: black; extra == 'dev'
Requires-Dist: black[jupyter]; extra == 'dev'
Requires-Dist: pydocstyle; extra == 'dev'
Requires-Dist: pyright; extra == 'dev'
Requires-Dist: pytest; extra == 'dev'
Requires-Dist: pytest-asyncio; extra == 'dev'
Requires-Dist: pytest-cov; extra == 'dev'
Provides-Extra: extract
Requires-Dist: langextract; extra == 'extract'
